{
  "signalKUrl": "http://localhost:3000",
  "signalKStream": "targeted",
  "signalKToken": "",
  "accessRequest": {},
  "rejectUnauthorized": false,
  "listenHost": "0.0.0.0",
  "listenPort": 3420,
  "piperBinary": "./piper/piper",
  "audioPlayer": "aplay",
  "voicesDir": "./voices",
  "voice": "en_GB-alan-medium",
  "speakerId": -1,
  "dedupeSeconds": 2,
  "stereoPing": true,
  "pingFrequencyHz": 880,
  "pingSmallFrequencyHz": 1100,
  "pingMediumFrequencyHz": 760,
  "pingLargeFrequencyHz": 440,
  "pingDurationMs": 180,
  "pingVolume": 2.2,
  "pingDoubleGapMs": 90,
  "pingSweepRatio": 0.72,
  "pingHarmonic": 0.18,
  "pingSpeechGapMs": 0,
  "debug": false,
  "volumeCommand": "",
  "enabled": true
}
